setup.py
radiosoma/__init__.py
radiosoma.egg-info/PKG-INFO
radiosoma.egg-info/SOURCES.txt
radiosoma.egg-info/dependency_links.txt
radiosoma.egg-info/top_level.txt