Metadata-Version: 2.1
Name: radiosoma
Version: 0.0.1
Summary: SomaFM python api
Home-page: https://github.com/OpenJarbas/radiosoma
Author: JarbasAi
License: Apache2
Platform: UNKNOWN
